LICENSE
README.md
setup.py
style_print/__init__.py
style_print/style_print.py
style_print.egg-info/PKG-INFO
style_print.egg-info/SOURCES.txt
style_print.egg-info/dependency_links.txt
style_print.egg-info/entry_points.txt
style_print.egg-info/requires.txt
style_print.egg-info/top_level.txt