Metadata-Version: 2.1
Name: style-print
Version: 2023.2.11
Summary: Print with style from the command line!
Home-page: https://github.com/egeakman/style-print
Download-URL: https://github.com/egeakman/style-print/archive/2023.2.11.tar.gz
Author: Ege Akman
Author-email: me@egeakman.dev
License: AGPLv3
Project-URL: Homepage, https://github.com/egeakman/style-print
Project-URL: Issues, https://github.com/egeakman/style-print/issues
Keywords: print,console,terminal,style,color,printy,utility
Classifier: Topic :: Utilities
Classifier: Programming Language :: Python :: 3 :: Only
Classifier: Development Status :: 5 - Production/Stable
Classifier: Environment :: Console
Classifier: License :: OSI Approved :: GNU Affero General Public License v3 or later (AGPLv3+)
Classifier: Operating System :: Microsoft :: Windows
Classifier: Operating System :: POSIX :: Linux
Classifier: Operating System :: MacOS :: MacOS X
Requires-Python: >=3.5
License-File: LICENSE
